{
  "run_name": "run_1772543961",
  "question_index": 2,
  "question_id": "4",
  "split": "train",
  "sample_id": 1,
  "final_reward": 0.0,
  "passed": false,
  "elapsed_seconds": 11.159265041351318,
  "response": "To solve this problem, we need to compute for each possible value of `k` (from 0 to N) the number of strings of length M such that their **longest common subsequence (LCS)** with the given string S has a length exactly equal to `k`.\n\n### Key Insight\nThe LCS of two strings is defined as the longest sequence that appears in both in the same order but not necessarily consecutively. We are interested in finding all strings of length M that have an LCS of certain lengths with S.\n\nWe will use **dynamic programming** to track how many strings can form a certain LCS length at each step.\n\nLet’s define:\n- `dp[i][j]`: the number of ways to form an LCS of length `j` using the first `i` characters of the target string S.\n\nFor each character in S, and for each possible LCS length up to M, we update our DP table based on whether or not the current character matches with any in the new string.\n\nFinally, after processing all characters in S, we count how many of the total `26^M` strings result in an exact LCS of length `k` for each `k`. We take modulo `998244353`.\n\n### Implementation Steps\n1. Read input values (N, M, S).\n2. Initialize a DP array where `dp[j]` represents the number of strings of length `M` that produce an LCS of length `j` with S.\n3. Iterate through all characters of S and update the DP array accordingly.\n4. After processing all characters, calculate the result for each k (modulo 998244353).\n\nNow, here is the complete and efficient Python code:\n\n```python\nMOD = 998244353\n\ndef main():\n    import sys\n    input = sys.stdin.read\n    data = input().split()\n    \n    N = int(data[0])\n    M = int(data[1])\n    S = data[2]\n    \n    # dp[j] = number of strings of length M that have LCS of length j with S\n    dp = [0] * (N + 1)\n    dp[0] = 1  # base case: empty string has LCS of 0 with any string\n    \n    for ch in S:\n        new_dp = [0] * (N + 1)\n        for j in range(N + 1):\n            # Case 1: we don't include ch in the LCS\n            new_dp[j] += dp[j] * 25  # append a character that is not ch\n            new_dp[j] %= MOD\n            \n            # Case 2: we include ch in the LCS if possible\n            if j > 0:\n                new_dp[j] += dp[j - 1]\n                new_dp[j] %= MOD\n        \n        dp = new_dp\n    \n    # Now calculate the final answer for each k from 0 to N\n    # The answer for k = i is (dp[i] - dp[i+1]) % MOD, since dp[i] counts all strings with LCS >= i\n    ans = [0] * (N + 1)\n    # dp[N] contains all strings with LCS exactly N\n    ans[N] = dp[N]\n    \n    for i in range(N - 1, -1, -1):\n        ans[i] = (dp[i] - ans[i + 1]) % MOD\n    \n    print(' '.join(map(str, ans)))\n\nif __name__ == \"__main__\":\n    main()\n```\n\nThis solution runs efficiently even for the maximum constraints (`N = 10`, `M = 100`) and leverages dynamic programming to count the required cases in O(N^2) time, which is feasible."
}