{
  "run_name": "run_1772552001",
  "question_index": 4,
  "question_id": "11",
  "split": "train",
  "sample_id": 13,
  "final_reward": 1.0,
  "passed": true,
  "elapsed_seconds": 13.576268672943115,
  "response": "### Step 1: Understand the Problem\n\nWe are given:\n- $ N $ people, each numbered from $ 1 $ to $ N $\n- Each person has a **bib number** $ Q_i $\n- Each person is staring at another person $ P_i $\n\nThe goal is to find, for each bib number $ i $, the bib number of the person that they are staring at.\n\nKey observations:\n- We have two arrays, $ P $ (staring direction) and $ Q $ (bib numbers)\n- $ P_i $ indicates the **person number** that person $ i $ is staring at\n- $ Q_i $ indicates the **bib number** of person $ i $\n- So, $ S_i $ (the answer for bib number $ i $) should be the **bib number** of the person that the person with bib number $ i $ is staring at\n\nThis is a mapping problem: we need to map the **bib numbers** to the **stared-at bib numbers**\n\n### Step 2: Designing the Algorithm\n\nThe key is to:\n1. Create a dictionary or array to map each person's bib number to their identity\n   - Given $ Q $, we can create a mapping from bib number to person index\n2. Use this mapping to determine which bib number corresponds to the person someone is staring at\n\nFor example:\n- If $ Q_3 = 1 $, then person with bib number 1 is the same as person 3\n- For $ P_3 = 2 $, person 3 is staring at person 2\n- The bib number of the person being stared at is $ Q_{P_3} = Q_2 $\n\nThus, for each bib number $ i $, we compute:\n$$\nS_i = Q_{P_k}, \\text{ where } k \\text{ is the person whose bib number is } i\n$$\n\nThis gives us the final solution in linear time ($ O(N) $)\n\n### Step 3: Code Implementation\n\n```python\n# Read input\nimport sys\n\ndef main():\n    input = sys.stdin.read\n    data = input().split()\n    \n    N = int(data[0])\n    P = list(map(int, data[1:N+1]))\n    Q = list(map(int, data[N+1:2*N+1]))\n    \n    # Create a map from bib number to person index\n    bib_to_person = [0] * (N + 1)\n    for i in range(N):\n        bib_to_person[Q[i]] = i + 1  # Person indices are 1-based\n    \n    # Compute S_i for each bib number i\n    result = [0] * (N + 1)\n    for i in range(1, N + 1):\n        person_being_stared_at = P[bib_to_person[i] - 1]\n        result[i] = Q[person_being_stared_at - 1]\n    \n    # Print the result\n    print(' '.join(map(str, result[1:])))\n    \nif __name__ == \"__main__\":\n    main()\n```\n\n### Explanation of the Code:\n\n- We use a `bib_to_person` array to directly access the person index based on their bib number.\n- Then, for each bib number, we find who they are staring at using $ P $, and look up their bib number via $ Q $\n- The result is printed as a space-separated string\n\nThis code runs in $ O(N) $ time and uses $ O(N) $ space, which fits within the constraints."
}