{
  "run_name": "run_1772543238",
  "question_index": 4,
  "question_id": "11",
  "split": "train",
  "sample_id": 14,
  "final_reward": 1.0,
  "passed": true,
  "elapsed_seconds": 11.371495008468628,
  "response": "To solve this problem, we need to determine for each person wearing a bib of number `i`, the bib number of the person they are staring at. \n\nThe input consists of:\n- `N`: the number of people\n- `P_1 P_2 ... P_N`: the person each person is staring at (by their original number)\n- `Q_1 Q_2 ... Q_N`: the bib numbers worn by each person\n\nWe need to find for each bib number `i` (from 1 to N), which bib number the person wearing that bib is staring at.\n\n### Key Observations:\n- `P_i` represents the original number of the person that person `i` is staring at.\n- `Q_i` represents the bib number of person `i`.\n- So, if we want to find the bib number of the person being stared at by bib number `i`, we need to map from the bib numbers to the original numbers and then use `P` to find the person being stared at.\n\n### Steps to Solve:\n1. Read input values: `N`, `P`, and `Q`.\n2. Create a dictionary or list to map bib numbers to the original person indices.\n3. For each bib number `i`, find the original index using the `Q` list.\n4. Use the `P` list to get the original person number that the person is staring at.\n5. Finally, find the bib number of that person using the inverse mapping.\n6. Output the result for each bib number from 1 to N.\n\nHere is the complete Python code that implements this logic efficiently:\n\n```python\ndef main():\n    import sys\n    input = sys.stdin.read\n    data = input().split()\n    \n    N = int(data[0])\n    P = list(map(int, data[1:N+1]))\n    Q = list(map(int, data[N+1:2*N+1]))\n    \n    # Create a mapping from bib number to original person index\n    bib_to_person = [0] * (N + 1)\n    for i in range(N):\n        bib_to_person[Q[i]] = i + 1  # Original person number is i + 1 (1-based)\n\n    # Build the result array\n    result = [0] * (N + 1)  # result[bib_number] = answer for that bib\n    for i in range(1, N + 1):\n        original_person = bib_to_person[i]\n        person_being_stared_at = P[original_person - 1]\n        result[i] = Q[person_being_stared_at - 1]\n    \n    # Print the results for bib numbers 1 to N\n    print(' '.join(map(str, result[1:N+1])))\n\nif __name__ == \"__main__\":\n    main()\n```\n\n### Explanation:\n- `bib_to_person` creates a mapping from the bib number to the original person number (1-based).\n- We iterate over each bib number from 1 to N.\n- For each, we find the original person, determine who they're staring at using `P`, and then find the bib number of that person using the reverse mapping.\n- The time complexity is O(N), which is efficient enough for the given constraints (`N <= 3*10^5`)."
}