{
  "run_name": "run_1772551042",
  "question_index": 2,
  "question_id": "4",
  "split": "train",
  "sample_id": 4,
  "final_reward": 0.0,
  "passed": false,
  "elapsed_seconds": 24.601739168167114,
  "response": "```python\nimport sys\n\nMOD = 998244353\n\ndef main():\n    import sys\n    input = sys.stdin.read\n    data = input().split()\n    N = int(data[0])\n    M = int(data[1])\n    S = data[2]\n\n    # Precompute the positions of each character in S\n    from collections import defaultdict\n    pos = defaultdict(list)\n    for i, c in enumerate(S):\n        pos[c].append(i)\n\n    # dp[i][j] represents the number of strings of length j with LCS length i\n    dp = [[0] * (M + 1) for _ in range(N + 1)]\n    dp[0][0] = 1\n\n    for j in range(M):\n        for i in range(N + 1):\n            if dp[i][j] == 0:\n                continue\n            # Current string can add any character\n            dp[i][j + 1] = (dp[i][j + 1] + dp[i][j] * 25) % MOD\n            # Check if adding a character that is in S can increase the LCS\n            for c in pos:\n                if i < N:\n                    # Find the index of the current character in S\n                    last_pos = pos[c][-1]\n                    # Compare with the position of S[i]\n                    if last_pos >= pos[S[i]] or last_pos == pos[S[i]]:\n                        dp[i + 1][j + 1] = (dp[i + 1][j + 1] + dp[i][j]) % MOD\n\n    ans = [0] * (N + 1)\n    for i in range(N + 1):\n        ans[i] = dp[i][M]\n    \n    print(' '.join(map(str, ans)))\n\nif __name__ == \"__main__\":\n    main()\n```"
}