{
  "run_name": "run_1772528834",
  "question_index": 11,
  "question_id": "29",
  "split": "train",
  "sample_id": 12,
  "final_reward": 0.0,
  "passed": false,
  "elapsed_seconds": 50.41343593597412,
  "response": "```python\nimport sys\nfrom itertools import product\n\ndef main():\n    import sys\n    input = sys.stdin.read\n    data = input().split()\n    \n    H = int(data[0])\n    W = int(data[1])\n    grid = data[2:2+H]\n    \n    # Convert each row to a list of integers\n    grid = [list(map(int, list(row))) for row in grid]\n    \n    # Precompute the number of 1s in each row\n    row_sums = [sum(row) for row in grid]\n    \n    # Try all possible combinations of flipping columns (W <= 18)\n    min_total = float('inf')\n    for flip_cols in product([0, 1], repeat=W):\n        # Compute the new row sums after flipping selected columns\n        total_ones = 0\n        for i in range(H):\n            row_sum = row_sums[i]\n            for j in range(W):\n                if flip_cols[j]:\n                    row_sum = (row_sum + (1 - 2 * grid[i][j])) % 2\n            total_ones += row_sum\n        \n        min_total = min(min_total, total_ones)\n    \n    print(min_total)\n\nif __name__ == \"__main__\":\n    main()\n```"
}