{
  "run_name": "run_1772532349",
  "question_index": 4,
  "question_id": "11",
  "split": "train",
  "sample_id": 10,
  "final_reward": 1.0,
  "passed": true,
  "elapsed_seconds": 16.02944540977478,
  "response": "To solve this problem, we need to understand the relationship between bib numbers and the people wearing them. Here's a step-by-step breakdown:\n\n---\n\n### **Understanding the Problem**\n- We are given:\n  - `N`: The number of people.\n  - `P`: An array where `P[i]` is the person (1-based index) that person `i` is staring at.\n  - `Q`: An array where `Q[i]` is the bib number worn by person `i`.\n\n- The task is to compute an array `S` such that:\n  - `S[i]` is the bib number of the person that the person wearing bib `i` is staring at.\n\n---\n\n### **Key Observations**\n- For each person `i`, the bib number they wear is `Q[i]`. So, if `Q[i] = j`, then person `i` is wearing bib `j`.\n- Person `i` is staring at `P[i]`, but this person may have a different bib number.\n- We need to find for each bib number `j`, what is the bib number of the person that the person with bib `j` is staring at.\n\nThis implies we need to reindex `P` according to the bib numbers.\n\n---\n\n### **Algorithm**\n1. Create two mappings:\n   - A mapping from bib number to person index: `bib_to_person = {q: i+1 for i, q in enumerate(Q)}`.\n   - A mapping from person index to their stared person: `person_to_stared = P`.\n\n2. For each bib `j` in `1..N`:\n   - Find the person index: `person = bib_to_person[j]`.\n   - This person is staring at `stared_person = person_to_stared[person - 1]`.\n   - Now, find the bib number of that stared person: `S[j] = Q[stared_person - 1]`.\n\n---\n\n### **Complexity**\n- Time Complexity: **O(N)** — since we only process each entry once.\n- Space Complexity: **O(N)** — for the mappings.\n\nThis approach meets the constraints and runs efficiently within the time limit.\n\n---\n\n### **Python Code**\n\n```python\ndef main():\n    import sys\n    input = sys.stdin.read\n    data = input().split()\n    \n    N = int(data[0])\n    P = list(map(int, data[1:N+1]))\n    Q = list(map(int, data[N+1:2*N+1]))\n    \n    # Mapping from bib number to person index (1-based)\n    bib_to_person = {q: i + 1 for i, q in enumerate(Q)}\n    \n    # Result array\n    S = [0] * (N + 1)  # 1-based indexing\n\n    for bib in range(1, N + 1):\n        person = bib_to_person[bib]\n        stared_person = P[person - 1]\n        S[bib] = Q[stared_person - 1]\n\n    print(' '.join(map(str, S[1:])))  # Output S[1], S[2], ..., S[N]\n\nif __name__ == \"__main__\":\n    main()\n```\n\n---\n\n### **Explanation of Sample Input**\n\n#### Sample Input 1:\n```\n4\n4 3 2 1\n2 3 1 4\n```\n\n- Bib 1 is worn by person 3.\n- Person 3 is staring at person 2.\n- Bib of person 2 is 3.\n- Thus, the answer for bib 1 is 3.\n\nFollowing the same logic for all bibs gives the output:\n```\n3 4 1 2\n```\n\n---\n\nThis solution is clean, efficient, and handles all edge cases as required."
}