{
  "run_name": "run_1772540339",
  "question_index": 15,
  "question_id": "54",
  "split": "train",
  "sample_id": 9,
  "final_reward": 1.0,
  "passed": true,
  "elapsed_seconds": 8.78693151473999,
  "response": "To solve this problem, we need to simulate the process of determining ranks based on scores. The key idea is to repeatedly find the maximum score among people who have not yet received a rank, assign them the current rank value, and increment the rank appropriately.\n\n### Steps:\n1. **Input Reading**: Read the number of people `N` and their respective scores.\n2. **Initialize Variables**: \n   - A list `ranks` to store the final ranks of each person.\n   - A boolean list `determined` to track whether a person's rank has been determined.\n   - A variable `current_rank` initialized to 1.\n3. **Simulation Loop**:\n   - While there are undetermined people:\n     - Find the maximum score among those who are undetermined.\n     - Count the number of people with that maximum score.\n     - Assign the `current_rank` to all these people.\n     - Update `current_rank` by adding the count of these people.\n4. **Output**: Print the ranks of each person in the order they were inputted.\n\n### Time Complexity:\n- The time complexity is $O(N^2)$ since for every iteration, we may scan through all N elements to find the maximum. However, this is acceptable given the constraint $N \\leq 100$.\n\nNow, here is the complete Python solution:\n\n```python\ndef main():\n    import sys\n    input = sys.stdin.read\n    data = input().split()\n    \n    N = int(data[0])\n    P = list(map(int, data[1:N+1]))\n    \n    ranks = [0] * N\n    determined = [False] * N\n    current_rank = 1\n    \n    while True:\n        # Find the maximum score among undetermined people\n        max_score = -1\n        max_indices = []\n        for i in range(N):\n            if not determined[i] and P[i] > max_score:\n                max_score = P[i]\n                max_indices = [i]\n            elif not determined[i] and P[i] == max_score:\n                max_indices.append(i)\n        \n        if not max_indices:\n            break\n        \n        # Assign ranks\n        for i in max_indices:\n            ranks[i] = current_rank\n            determined[i] = True\n        \n        # Update current_rank\n        current_rank += len(max_indices)\n    \n    for rank in ranks:\n        print(rank)\n\nif __name__ == \"__main__\":\n    main()\n```"
}