{
  "run_name": "run_1772531341",
  "question_index": 14,
  "question_id": "53",
  "split": "train",
  "sample_id": 4,
  "final_reward": 1.0,
  "passed": true,
  "elapsed_seconds": 8.695586204528809,
  "response": "```python\nimport sys\ninput = sys.stdin.read\n\nMOD = 998244353\n\ndef main():\n    data = input().split()\n    N = int(data[0])\n    K = int(data[1])\n    A = list(map(int, data[2:2+N]))\n    \n    prefix = [0] * (N + 1)\n    for i in range(N):\n        prefix[i+1] = (prefix[i] + A[i]) % MOD\n    \n    result = 0\n    for l in range(N):\n        curr_sum = 0\n        for r in range(l, N):\n            curr_sum = (curr_sum + A[r]) % MOD\n            result = (result + pow(curr_sum, K, MOD)) % MOD\n    \n    print(result)\n\nif __name__ == \"__main__\":\n    main()\n```"
}